aioymaps.py
aioymaps-1.2.5.dist-info/LICENSE
aioymaps-1.2.5.dist-info/METADATA
aioymaps-1.2.5.dist-info/WHEEL
aioymaps-1.2.5.dist-info/top_level.txt
aioymaps-1.2.5.dist-info/RECORD
