Metadata-Version: 2.1
Name: aioymaps
Version: 1.2.5
Summary: Async client for Yandex Maps
Home-page: https://github.com/devbis/aioymaps/
Author: Ivan Belokobylskiy
Author-email: belokobylskij@gmail.com
Classifier: Programming Language :: Python :: 3.5
Classifier: Programming Language :: Python :: 3.6
Classifier: Programming Language :: Python :: 3.7
Classifier: Programming Language :: Python :: 3.8
Classifier: Programming Language :: Python :: 3.9
Classifier: Programming Language :: Python :: 3.10
Classifier: Programming Language :: Python :: 3.11
Classifier: Programming Language :: Python :: 3.12
Classifier: Programming Language :: Python :: 3 :: Only
Classifier: Topic :: Utilities
Classifier: License :: OSI Approved :: MIT License
License-File: LICENSE
Requires-Dist: aiohttp>=3.0.0
